aiopeplink/__init__.py
aiopeplink/peplink.py
aiopeplink/interfaces/__init__.py
aiopeplink/interfaces/connectivity.py
aiopeplink/models/__init__.py
aiopeplink/models/info.py
aiopeplink-0.0.2.dist-info/LICENSE
aiopeplink-0.0.2.dist-info/METADATA
aiopeplink-0.0.2.dist-info/WHEEL
aiopeplink-0.0.2.dist-info/top_level.txt
aiopeplink-0.0.2.dist-info/RECORD
